app/__init__.py
app/app.py
app/config.py
app/router.py
app/core/__init__.py
app/core/base.py
app/core/drawer.py
app/core/footer.py
app/core/header.py
app/core/left.py
app/core/middle.py
app/core/mobile.py
app/core/repository.py
app/core/right.py
app/helpers/__init__.py
app/helpers/app_config.py
app/helpers/css_helpers.py
app/helpers/nav_helpers.py
app/material/__init__.py
app/material/admonition.py
app/material/button.py
app/material/typography.py
app/states/__init__.py
app/states/drawerState.py
app/states/headerState.py
app/states/mainState.py
app/styles/__init__.py
app/styles/_admonition.py
app/styles/_base.py
app/styles/_button.py
app/styles/_markdown.py
app/utilities/__init__.py
app/utilities/rx_index.py
app/utilities/rx_page404.py
app/utilities/rx_template.py
reflexify-0.0.9.data/data/app/app.py
reflexify-0.0.9.data/data/app/config.py
reflexify-0.0.9.data/data/app/router.py
reflexify_scripts/__init__.py
reflexify_scripts/build.py
reflexify_scripts/create.py
tests/__init__.py
tests/test_config.py
tests/test_helpers.py
reflexify-0.0.9.dist-info/LICENSE
reflexify-0.0.9.dist-info/METADATA
reflexify-0.0.9.dist-info/WHEEL
reflexify-0.0.9.dist-info/entry_points.txt
reflexify-0.0.9.dist-info/top_level.txt
reflexify-0.0.9.dist-info/RECORD
