Metadata-Version: 2.1
Name: reflexify
Version: 0.0.9
Summary: Document, build, and showcase - all in one place, all in Python.
Home-page: https://github.com/LineIndent/reflexify
Author: S. Ahmad P. Hakimi
Author-email: pourhakimi@pm.me
Keywords: python web template,web application,documentation
Classifier: Programming Language :: Python :: 3
Classifier: License :: OSI Approved :: MIT License
Classifier: Operating System :: OS Independent
License-File: LICENSE
Requires-Dist: click >=8.1.3
Requires-Dist: reflex >=0.2.4
Requires-Dist: beautifulsoup4 >=4.12.2
